material_icons
