Metadata-Version: 2.4
Name: python-material-icons
Version: 0.3.1
Summary: Use Google's Material Icons in your Python applications
Author-email: "Chris L." <stylesuxx@gmail.com>
Maintainer-email: "Chris L." <stylesuxx@gmail.com>
License-Expression: MIT
Project-URL: Homepage, https://github.com/stylesuxx/python-material-icons
Project-URL: Repository, https://github.com/stylesuxx/python-material-icons
Project-URL: Documentation, https://github.com/stylesuxx/python-material-icons#readme
Project-URL: Issues, https://github.com/stylesuxx/python-material-icons/issues
Project-URL: Changelog, https://github.com/stylesuxx/python-material-icons/releases
Keywords: material,icons,google,design,svg,png
Classifier: Development Status :: 4 - Beta
Classifier: Intended Audience :: Developers
Classifier: Operating System :: OS Independent
Classifier: Programming Language :: Python :: 3
Classifier: Programming Language :: Python :: 3.8
Classifier: Programming Language :: Python :: 3.9
Classifier: Programming Language :: Python :: 3.10
Classifier: Programming Language :: Python :: 3.11
Classifier: Programming Language :: Python :: 3.12
Classifier: Topic :: Multimedia :: Graphics
Classifier: Topic :: Software Development :: Libraries :: Python Modules
Classifier: Topic :: Software Development :: User Interfaces
Requires-Python: >=3.8
License-File: LICENSE
Requires-Dist: cairosvg>=2.8.2
Provides-Extra: dev
Requires-Dist: pytest>=7.0; extra == "dev"
Requires-Dist: pytest-cov; extra == "dev"
Requires-Dist: black; extra == "dev"
Requires-Dist: flake8; extra == "dev"
Requires-Dist: mypy; extra == "dev"
Provides-Extra: examples
Requires-Dist: pygame-ce>=2.5.5; extra == "examples"
Requires-Dist: pillow>=11.3.0; extra == "examples"
Dynamic: license-file
